sare/__init__.py
sare-0.1.dist-info/METADATA
sare-0.1.dist-info/WHEEL
sare-0.1.dist-info/license.txt
sare-0.1.dist-info/top_level.txt
sare-0.1.dist-info/RECORD
