Metadata-Version: 2.1
Name: sare
Version: 0.1
Summary: i love you
Author: sare
Author-email: 
Classifier: Programming Language :: Python :: 3
Classifier: License :: OSI Approved :: MIT License
Classifier: Operating System :: OS Independent
License-File: license.txt
